lfortune/__init__.py
lfortune/abstract/__init__.py
lfortune/abstract/fortune.py
lfortune/abstract/fortune_data.py
lfortune/abstract/fortune_source.py
lfortune/cli/__init__.py
lfortune/cli/arguments.py
lfortune/cli/cli.py
lfortune/cli/functions.py
lfortune/cli/input_parser.py
lfortune/cli/tests/__init__.py
lfortune/cli/tests/test_input_parser.py
lfortune/daemon/__init__.py
lfortune/daemon/app.py
lfortune/data/test-fortunes
lfortune/fortune/__init__.py
lfortune/fortune/config.py
lfortune/fortune/config_values.py
lfortune/fortune/db_randomizer.py
lfortune/fortune/drawing_machine.py
lfortune/fortune/factory.py
lfortune/fortune/fortune.py
lfortune/fortune/indexer.py
lfortune/fortune/validator.py
lfortune/fortune/drawing_machines/__init__.py
lfortune/fortune/drawing_machines/normalize_source_list.py
lfortune/fortune/drawing_machines/simple.py
lfortune/fortune/index/__init__.py
lfortune/fortune/index/data.py
lfortune/fortune/tests/__init__.py
lfortune/fortune/tests/test_fortune.py
lfortune/fortune/tests/test_indexer.py
lfortune/fortune/validators/__init__.py
lfortune/fortune/validators/existence.py
lfortune/fortune/validators/probability.py
lfortune/fortune/validators/without_dots.py
lfortune-0.3.2.dist-info/LICENSE
lfortune-0.3.2.dist-info/METADATA
lfortune-0.3.2.dist-info/WHEEL
lfortune-0.3.2.dist-info/entry_points.txt
lfortune-0.3.2.dist-info/top_level.txt
lfortune-0.3.2.dist-info/RECORD
