Metadata-Version: 2.1
Name: lfortune
Version: 0.3.2
Summary: Good old fortunes!
Home-page: https://github.com/lbacik/fortune
Author: Łukasz Bacik
Author-email: mail@luka.sh
License: GPLv3
Platform: UNKNOWN
Classifier: Environment :: Console
Classifier: Operating System :: OS Independent
Classifier: Programming Language :: Python
License-File: LICENSE
Requires-Dist: simple-value-object (==1.5)
